Metadata-Version: 2.1
Name: configurable-objects
Version: 0.0.1
Summary: Library for making it easy to manage parameters of objects via dictionaries or JSON.
Home-page: https://github.com/fracpete/configurable-objects
Author: Peter "fracpete" Reutemann
Author-email: configurable-objects@fracpete.org
License: MIT
Classifier: Development Status :: 4 - Beta
Classifier: License :: OSI Approved :: MIT License
Classifier: Topic :: Software Development
Classifier: Programming Language :: Python :: 3
License-File: LICENSE
